BibliotecaRIT/BibliotecaRITFachada.py
BibliotecaRIT/__init__.py
BibliotecaRIT/Sources/Requisicao.py
BibliotecaRIT/Sources/__init__.py
BibliotecaRIT/Sources/controladoras/ControladoraCalculoRelevancia.py
BibliotecaRIT/Sources/controladoras/ControladoraExportacaoDados.py
BibliotecaRIT/Sources/controladoras/ControladoraExtracaoDados.py
BibliotecaRIT/Sources/controladoras/__init__.py
BibliotecaRIT/Sources/entidades/Comentario.py
BibliotecaRIT/Sources/entidades/Projeto.py
BibliotecaRIT/Sources/entidades/Topico.py
BibliotecaRIT/Sources/entidades/__init__.py
BibliotecaRIT/Sources/interfaces/FiltroExtracaoStrategy.py
BibliotecaRIT/Sources/interfaces/VisaoStrategy.py
BibliotecaRIT/Sources/interfaces/__init__.py
testeBibRit-1.0.0.dist-info/LICENSE
testeBibRit-1.0.0.dist-info/METADATA
testeBibRit-1.0.0.dist-info/WHEEL
testeBibRit-1.0.0.dist-info/top_level.txt
testeBibRit-1.0.0.dist-info/RECORD
